psense/__init__.py
psense/observe.py
psense/py.typed
psense/measure/__init__.py
psense/measure/base.py
psense/measure/host.py
psense/measure/nv.py
psense-0.1.0.dist-info/LICENSE
psense-0.1.0.dist-info/METADATA
psense-0.1.0.dist-info/WHEEL
psense-0.1.0.dist-info/top_level.txt
psense-0.1.0.dist-info/RECORD
