Metadata-Version: 2.1
Name: psense
Version: 0.1.0
Summary: process state monitoring tools
Author-email: "Vladislav A. Proskurov" <rilshok@pm.me>
License: MIT
Project-URL: Homepage, https://github.com/rilshok/psense
Project-URL: Repository, https://github.com/rilshok/psense.git
Project-URL: Issues, https://github.com/rilshok/psense/issues
Requires-Python: >=3.10
License-File: LICENSE
Requires-Dist: typing-extensions >=4.8.0
Requires-Dist: nvitop >=1.3.2
Provides-Extra: dev
Requires-Dist: psense[lint,test] ; extra == 'dev'
Provides-Extra: lint
Requires-Dist: mypy >=1.7.1 ; extra == 'lint'
Requires-Dist: ruff >=0.6.3 ; extra == 'lint'
Requires-Dist: types-pytz >=2024.1 ; extra == 'lint'
Requires-Dist: types-psutil ; extra == 'lint'
Provides-Extra: test
Requires-Dist: pytest >=8.2.2 ; extra == 'test'
Requires-Dist: pytest-cov >=5.0.0 ; extra == 'test'
